sas_dict/__init__.py
sas_dict/cli.py
sas_dict-0.1.0.dist-info/METADATA
sas_dict-0.1.0.dist-info/WHEEL
sas_dict-0.1.0.dist-info/entry_points.txt
sas_dict-0.1.0.dist-info/RECORD
