Metadata-Version: 2.4
Name: sas-dict
Version: 0.1.0
Summary: Fetches and prints definitions for a given word
Project-URL: Repository, https://github.com/sashi202/sas-dict
Author-email: Tommy <tommy@nobody.com>
Requires-Python: >=3.13
Requires-Dist: httpx>=0.28.1
Requires-Dist: pytest>=8.3.5
Requires-Dist: ruff>=0.11.7
